desimodels-0.1.0.dist-info/METADATA
desimodels-0.1.0.dist-info/WHEEL
desimodels-0.1.0.dist-info/entry_points.txt
desimodels-0.1.0.dist-info/licenses/LICENSE
desimodels/__init__.py
desimodels/queues/__init__.py
desimodels/queues/mmc/__init__.py
desimodels/queues/mmc/_desimpy.py
desimodels-0.1.0.dist-info/RECORD
