Metadata-Version: 2.1
Name: DESiModels
Version: 0.1.0
Summary: Ready-to-use discrete event simulation models.
Author-Email: galenseilis <galen.seilis@seilis.ca>
License: Apache-2.0
Requires-Python: >=3.12
